job_shop_lib/__init__.py
job_shop_lib/_base_solver.py
job_shop_lib/_job_shop_instance.py
job_shop_lib/_operation.py
job_shop_lib/_schedule.py
job_shop_lib/_scheduled_operation.py
job_shop_lib/benchmarking/__init__.py
job_shop_lib/benchmarking/_load_benchmark.py
job_shop_lib/benchmarking/benchmark_instances.json
job_shop_lib/constraint_programming/__init__.py
job_shop_lib/constraint_programming/_ortools_solver.py
job_shop_lib/dispatching/__init__.py
job_shop_lib/dispatching/_dispatcher.py
job_shop_lib/dispatching/_dispatcher_observer_config.py
job_shop_lib/dispatching/_factories.py
job_shop_lib/dispatching/_history_observer.py
job_shop_lib/dispatching/_optimal_operations_observer.py
job_shop_lib/dispatching/_ready_operation_filters.py
job_shop_lib/dispatching/_start_time_calculators.py
job_shop_lib/dispatching/_unscheduled_operations_observer.py
job_shop_lib/dispatching/feature_observers/__init__.py
job_shop_lib/dispatching/feature_observers/_composite_feature_observer.py
job_shop_lib/dispatching/feature_observers/_dates_observer.py
job_shop_lib/dispatching/feature_observers/_duration_observer.py
job_shop_lib/dispatching/feature_observers/_earliest_start_time_observer.py
job_shop_lib/dispatching/feature_observers/_factory.py
job_shop_lib/dispatching/feature_observers/_feature_observer.py
job_shop_lib/dispatching/feature_observers/_is_completed_observer.py
job_shop_lib/dispatching/feature_observers/_is_ready_observer.py
job_shop_lib/dispatching/feature_observers/_is_scheduled_observer.py
job_shop_lib/dispatching/feature_observers/_position_in_job_observer.py
job_shop_lib/dispatching/feature_observers/_remaining_operations_observer.py
job_shop_lib/dispatching/rules/__init__.py
job_shop_lib/dispatching/rules/_dispatching_rule_factory.py
job_shop_lib/dispatching/rules/_dispatching_rule_solver.py
job_shop_lib/dispatching/rules/_dispatching_rules_functions.py
job_shop_lib/dispatching/rules/_machine_chooser_factory.py
job_shop_lib/dispatching/rules/_utils.py
job_shop_lib-1.7.0.dist-info/LICENSE
job_shop_lib-1.7.0.dist-info/METADATA
job_shop_lib-1.7.0.dist-info/WHEEL
job_shop_lib-1.7.0.dist-info/RECORD
