Metadata-Version: 2.1
Name: job-shop-lib
Version: 1.7.0
Summary: An easy-to-use and modular Python library for the Job Shop Scheduling Problem (JSSP)
License: MIT
Author: Pabloo22
Author-email: pablete.arino@gmail.com
Requires-Python: >=3.10,<4.0
Classifier: License :: OSI Approved :: MIT License
Classifier: Programming Language :: Python :: 3
Classifier: Programming Language :: Python :: 3.10
Classifier: Programming Language :: Python :: 3.11
Classifier: Programming Language :: Python :: 3.12
Provides-Extra: pygraphviz
Requires-Dist: gymnasium (>=1.0.0,<2.0.0)
Requires-Dist: imageio[ffmpeg] (>=2.34.1,<3.0.0)
Requires-Dist: matplotlib (>=3,<4)
Requires-Dist: networkx (>=3,<4)
Requires-Dist: numpy (>=1.26.4,<3.0.0)
Requires-Dist: ortools (>=9.9,<9.13)
Requires-Dist: pyarrow (>=15,<21)
Requires-Dist: pygraphviz (>=1.12,<2.0) ; extra == "pygraphviz"
Requires-Dist: simanneal (>=0.5.0,<0.6.0)
